pkg1/__init__.py
pkg1/__main__.py
pkg1/file1.py
pkg1/file2.py
pkg2/__init__.py
pkg2/file3.py
pkg2/file4.py
anis_package-1.0.0.dist-info/METADATA
anis_package-1.0.0.dist-info/WHEEL
anis_package-1.0.0.dist-info/entry_points.txt
anis_package-1.0.0.dist-info/top_level.txt
anis_package-1.0.0.dist-info/RECORD
