Metadata-Version: 2.1
Name: anis-package
Version: 1.0.0
Summary: this is a test package
Home-page: UNKNOWN
Author: anisanis611
Author-email: anis.dhouieb@gmail.com
License: MIT
Platform: UNKNOWN
